ordeq_cli_runner/__init__.py
ordeq_cli_runner/_version.py
ordeq_cli_runner/py.typed
ordeq_cli_runner-2.1.0.dist-info/licenses/LICENSE
ordeq_cli_runner-2.1.0.dist-info/METADATA
ordeq_cli_runner-2.1.0.dist-info/WHEEL
ordeq_cli_runner-2.1.0.dist-info/entry_points.txt
ordeq_cli_runner-2.1.0.dist-info/top_level.txt
ordeq_cli_runner-2.1.0.dist-info/RECORD
