Metadata-Version: 2.4
Name: ordeq_cli_runner
Version: 2.1.0
Summary: Command line interface for the Ordeq runner
Author: Niels Neerhoff, Simon Brugman
Maintainer: Niels Neerhoff, Simon Brugman
License-Expression: MIT
Requires-Python: >=3.10
License-File: LICENSE
Requires-Dist: ordeq>=1.3.0
Dynamic: license-file
